CHANGELOG.md
LICENSE
MANIFEST.in
README.md
setup.cfg
setup.py
witchfinder/__init__.py
witchfinder.egg-info/PKG-INFO
witchfinder.egg-info/SOURCES.txt
witchfinder.egg-info/dependency_links.txt
witchfinder.egg-info/top_level.txt
witchfinder/carve/__init__.py
witchfinder/carve/carvers.py
witchfinder/carve/common.py
witchfinder/carve/extractors.py
witchfinder/carve/providers.py
witchfinder/validate/__init__.py
witchfinder/validate/validator.py